README.md
setup.py
scour/__init__.py
scour/scour - Kopie.py
scour/scour.py
scour/svg_regex.py
scour/svg_transform.py
scour/yocto_css.py
scour.egg-info/PKG-INFO
scour.egg-info/SOURCES.txt
scour.egg-info/dependency_links.txt
scour.egg-info/entry_points.txt
scour.egg-info/requires.txt
scour.egg-info/top_level.txt
scour.egg-info/zip-safe