Metadata-Version: 1.1
Name: scour
Version: 0.38.1
Summary: Scour SVG Optimizer
Home-page: https://github.com/scour-project/scour
Author: Jeff Schiller
Author-email: codedread@gmail.com
License: Apache License 2.0
Keywords: svg optimizer
Platform: Any
Classifier: License :: OSI Approved :: Apache Software License
Classifier: Development Status :: 5 - Production/Stable
Classifier: Environment :: Console
Classifier: Intended Audience :: Developers
Classifier: Intended Audience :: System Administrators
Classifier: Operating System :: OS Independent
Classifier: Programming Language :: Python
Classifier: Topic :: Internet
Classifier: Topic :: Software Development :: Build Tools
Classifier: Topic :: Software Development :: Pre-processors
Classifier: Topic :: Multimedia :: Graphics :: Graphics Conversion
Classifier: Topic :: Utilities
